Workbook

Sheet Start Here
B2: Simple Money Playbook
B4: Debt Payoff Date Calculator
B6: Make this yours first
B7: This copy is view-only. Go to File -> Make a copy to save your own editable version, then fill in your own debts.
B9: What it does
B10: List every debt with its balance, interest rate, and minimum payment, then add whatever extra you can pay each month. It simulates paying them off month by month and tells you the exact date you'll be debt-free and the total interest you'll pay.
B12: Avalanche vs. Snowball
B13: Type either method in the blue Method cell. Avalanche attacks the highest interest rate first (usually the least interest paid). Snowball attacks the smallest balance first (fastest first win). Switch between them and watch the date and interest change.
B15: How to use it
B16: 1. Make your own copy. 2. Fill the blue cells on the 'Calculator' tab: your debts, and your extra monthly payment. 3. Everything else, including the chart and your debt-free date, updates itself.
B18: About the numbers
B19: This assumes you keep paying the same total each month (as a debt is cleared, its payment rolls onto the next one). Interest is estimated monthly from the rate you enter. Educational only, not financial advice; for decisions about your own money, talk to a qualified professional.
B21: More free lessons + recipes: simplemoneyplaybook.com

Sheet Calculator
B1: Debt Payoff Date Calculator
B2: List your debts, add whatever extra you can pay, and see the exact month you'll be free. Switch Avalanche/Snowball to compare.
B4: The plan | E4: Your payoff
B5: Method | C5: Avalanche | E5: Debt-free date | G5: =IF(SUM(C11:C28)=0,"-",IF(Engine!$CD$1=0,"30+ yrs",EDATE(TODAY(),Engine!$CD$1)))
B6: Extra monthly payment | C6: 250 | E6: Time to freedom | G6: =IF(SUM(C11:C28)=0,"-",IF(Engine!$CD$1=0,">360 mo",Engine!$CD$1&" mo"))
E7: Total interest you'll pay | G7: =SUM(Engine!$BZ$4:$BZ$363)
E8: Total you'll pay | G8: =SUM(C11:C28)+SUM(Engine!$BZ$4:$BZ$363)
B10: Debt | C10: Balance | D10: APR % | E10: Min payment | F10: Priority | G10: Paid off by
B11: Credit Card | C11: 4800 | D11: 22.9 | E11: 120 | F11: =IF(B11="","",RANK(J11,$J$11:$J$28,1)) | G11: =IF(B11="","",IF(MINIFS(Engine!$A$4:$A$363,Engine!$BD$4:$BD$363,"<=0.01")=0,"30+ yrs",EDATE(TODAY(),MINIFS(Engine!$A$4:$A$363,Engine!$BD$4:$BD$363,"<=0.01")))) | J11: =IF(B11="",1000000000+ROW()*0.000001,IF($C$5="Snowball",C11,-D11)+ROW()*0.000001)
B12: Car Loan | C12: 9500 | D12: 6.5 | E12: 210 | F12: =IF(B12="","",RANK(J12,$J$11:$J$28,1)) | G12: =IF(B12="","",IF(MINIFS(Engine!$A$4:$A$363,Engine!$BE$4:$BE$363,"<=0.01")=0,"30+ yrs",EDATE(TODAY(),MINIFS(Engine!$A$4:$A$363,Engine!$BE$4:$BE$363,"<=0.01")))) | J12: =IF(B12="",1000000000+ROW()*0.000001,IF($C$5="Snowball",C12,-D12)+ROW()*0.000001)
B13: Student Loan | C13: 14000 | D13: 5.2 | E13: 150 | F13: =IF(B13="","",RANK(J13,$J$11:$J$28,1)) | G13: =IF(B13="","",IF(MINIFS(Engine!$A$4:$A$363,Engine!$BF$4:$BF$363,"<=0.01")=0,"30+ yrs",EDATE(TODAY(),MINIFS(Engine!$A$4:$A$363,Engine!$BF$4:$BF$363,"<=0.01")))) | J13: =IF(B13="",1000000000+ROW()*0.000001,IF($C$5="Snowball",C13,-D13)+ROW()*0.000001)
F14: =IF(B14="","",RANK(J14,$J$11:$J$28,1)) | G14: =IF(B14="","",IF(MINIFS(Engine!$A$4:$A$363,Engine!$BG$4:$BG$363,"<=0.01")=0,"30+ yrs",EDATE(TODAY(),MINIFS(Engine!$A$4:$A$363,Engine!$BG$4:$BG$363,"<=0.01")))) | J14: =IF(B14="",1000000000+ROW()*0.000001,IF($C$5="Snowball",C14,-D14)+ROW()*0.000001)
F15: =IF(B15="","",RANK(J15,$J$11:$J$28,1)) | G15: =IF(B15="","",IF(MINIFS(Engine!$A$4:$A$363,Engine!$BH$4:$BH$363,"<=0.01")=0,"30+ yrs",EDATE(TODAY(),MINIFS(Engine!$A$4:$A$363,Engine!$BH$4:$BH$363,"<=0.01")))) | J15: =IF(B15="",1000000000+ROW()*0.000001,IF($C$5="Snowball",C15,-D15)+ROW()*0.000001)
F16: =IF(B16="","",RANK(J16,$J$11:$J$28,1)) | G16: =IF(B16="","",IF(MINIFS(Engine!$A$4:$A$363,Engine!$BI$4:$BI$363,"<=0.01")=0,"30+ yrs",EDATE(TODAY(),MINIFS(Engine!$A$4:$A$363,Engine!$BI$4:$BI$363,"<=0.01")))) | J16: =IF(B16="",1000000000+ROW()*0.000001,IF($C$5="Snowball",C16,-D16)+ROW()*0.000001)
F17: =IF(B17="","",RANK(J17,$J$11:$J$28,1)) | G17: =IF(B17="","",IF(MINIFS(Engine!$A$4:$A$363,Engine!$BJ$4:$BJ$363,"<=0.01")=0,"30+ yrs",EDATE(TODAY(),MINIFS(Engine!$A$4:$A$363,Engine!$BJ$4:$BJ$363,"<=0.01")))) | J17: =IF(B17="",1000000000+ROW()*0.000001,IF($C$5="Snowball",C17,-D17)+ROW()*0.000001)
F18: =IF(B18="","",RANK(J18,$J$11:$J$28,1)) | G18: =IF(B18="","",IF(MINIFS(Engine!$A$4:$A$363,Engine!$BK$4:$BK$363,"<=0.01")=0,"30+ yrs",EDATE(TODAY(),MINIFS(Engine!$A$4:$A$363,Engine!$BK$4:$BK$363,"<=0.01")))) | J18: =IF(B18="",1000000000+ROW()*0.000001,IF($C$5="Snowball",C18,-D18)+ROW()*0.000001)
F19: =IF(B19="","",RANK(J19,$J$11:$J$28,1)) | G19: =IF(B19="","",IF(MINIFS(Engine!$A$4:$A$363,Engine!$BL$4:$BL$363,"<=0.01")=0,"30+ yrs",EDATE(TODAY(),MINIFS(Engine!$A$4:$A$363,Engine!$BL$4:$BL$363,"<=0.01")))) | J19: =IF(B19="",1000000000+ROW()*0.000001,IF($C$5="Snowball",C19,-D19)+ROW()*0.000001)
F20: =IF(B20="","",RANK(J20,$J$11:$J$28,1)) | G20: =IF(B20="","",IF(MINIFS(Engine!$A$4:$A$363,Engine!$BM$4:$BM$363,"<=0.01")=0,"30+ yrs",EDATE(TODAY(),MINIFS(Engine!$A$4:$A$363,Engine!$BM$4:$BM$363,"<=0.01")))) | J20: =IF(B20="",1000000000+ROW()*0.000001,IF($C$5="Snowball",C20,-D20)+ROW()*0.000001)
F21: =IF(B21="","",RANK(J21,$J$11:$J$28,1)) | G21: =IF(B21="","",IF(MINIFS(Engine!$A$4:$A$363,Engine!$BN$4:$BN$363,"<=0.01")=0,"30+ yrs",EDATE(TODAY(),MINIFS(Engine!$A$4:$A$363,Engine!$BN$4:$BN$363,"<=0.01")))) | J21: =IF(B21="",1000000000+ROW()*0.000001,IF($C$5="Snowball",C21,-D21)+ROW()*0.000001)
F22: =IF(B22="","",RANK(J22,$J$11:$J$28,1)) | G22: =IF(B22="","",IF(MINIFS(Engine!$A$4:$A$363,Engine!$BO$4:$BO$363,"<=0.01")=0,"30+ yrs",EDATE(TODAY(),MINIFS(Engine!$A$4:$A$363,Engine!$BO$4:$BO$363,"<=0.01")))) | J22: =IF(B22="",1000000000+ROW()*0.000001,IF($C$5="Snowball",C22,-D22)+ROW()*0.000001)
F23: =IF(B23="","",RANK(J23,$J$11:$J$28,1)) | G23: =IF(B23="","",IF(MINIFS(Engine!$A$4:$A$363,Engine!$BP$4:$BP$363,"<=0.01")=0,"30+ yrs",EDATE(TODAY(),MINIFS(Engine!$A$4:$A$363,Engine!$BP$4:$BP$363,"<=0.01")))) | J23: =IF(B23="",1000000000+ROW()*0.000001,IF($C$5="Snowball",C23,-D23)+ROW()*0.000001)
F24: =IF(B24="","",RANK(J24,$J$11:$J$28,1)) | G24: =IF(B24="","",IF(MINIFS(Engine!$A$4:$A$363,Engine!$BQ$4:$BQ$363,"<=0.01")=0,"30+ yrs",EDATE(TODAY(),MINIFS(Engine!$A$4:$A$363,Engine!$BQ$4:$BQ$363,"<=0.01")))) | J24: =IF(B24="",1000000000+ROW()*0.000001,IF($C$5="Snowball",C24,-D24)+ROW()*0.000001)
F25: =IF(B25="","",RANK(J25,$J$11:$J$28,1)) | G25: =IF(B25="","",IF(MINIFS(Engine!$A$4:$A$363,Engine!$BR$4:$BR$363,"<=0.01")=0,"30+ yrs",EDATE(TODAY(),MINIFS(Engine!$A$4:$A$363,Engine!$BR$4:$BR$363,"<=0.01")))) | J25: =IF(B25="",1000000000+ROW()*0.000001,IF($C$5="Snowball",C25,-D25)+ROW()*0.000001)
F26: =IF(B26="","",RANK(J26,$J$11:$J$28,1)) | G26: =IF(B26="","",IF(MINIFS(Engine!$A$4:$A$363,Engine!$BS$4:$BS$363,"<=0.01")=0,"30+ yrs",EDATE(TODAY(),MINIFS(Engine!$A$4:$A$363,Engine!$BS$4:$BS$363,"<=0.01")))) | J26: =IF(B26="",1000000000+ROW()*0.000001,IF($C$5="Snowball",C26,-D26)+ROW()*0.000001)
F27: =IF(B27="","",RANK(J27,$J$11:$J$28,1)) | G27: =IF(B27="","",IF(MINIFS(Engine!$A$4:$A$363,Engine!$BT$4:$BT$363,"<=0.01")=0,"30+ yrs",EDATE(TODAY(),MINIFS(Engine!$A$4:$A$363,Engine!$BT$4:$BT$363,"<=0.01")))) | J27: =IF(B27="",1000000000+ROW()*0.000001,IF($C$5="Snowball",C27,-D27)+ROW()*0.000001)
F28: =IF(B28="","",RANK(J28,$J$11:$J$28,1)) | G28: =IF(B28="","",IF(MINIFS(Engine!$A$4:$A$363,Engine!$BU$4:$BU$363,"<=0.01")=0,"30+ yrs",EDATE(TODAY(),MINIFS(Engine!$A$4:$A$363,Engine!$BU$4:$BU$363,"<=0.01")))) | J28: =IF(B28="",1000000000+ROW()*0.000001,IF($C$5="Snowball",C28,-D28)+ROW()*0.000001)
B30: =IF(SUM(C11:C28)=0,"Add your debts above to see your debt-free date.",IF(Engine!$CD$1=0,"With this plan the debt is not cleared within 30 years. Increase your extra payment to see a date.","You will be debt-free in "&Engine!$CD$1&" months, by "&TEXT(EDATE(TODAY(),Engine!$CD$1),"mmm yyyy")&", after paying $"&TEXT(SUM(Engine!$BZ$4:$BZ$363),"#,##0")&" in interest. Switch the method above to compare."))
B32: Priority shows the order this method pays your debts. Illustration only, not financial advice. simplemoneyplaybook.com

Sheet Engine
A1: Simulation engine (do not edit) | CD1: =MINIFS($A$4:$A$363,$BY$4:$BY$363,"<=0.01")
T2: =IF(Calculator!$B$11="",9999,Calculator!$F$11) | U2: =IF(Calculator!$B$12="",9999,Calculator!$F$12) | V2: =IF(Calculator!$B$13="",9999,Calculator!$F$13) | W2: =IF(Calculator!$B$14="",9999,Calculator!$F$14) | X2: =IF(Calculator!$B$15="",9999,Calculator!$F$15) | Y2: =IF(Calculator!$B$16="",9999,Calculator!$F$16) | Z2: =IF(Calculator!$B$17="",9999,Calculator!$F$17) | AA2: =IF(Calculator!$B$18="",9999,Calculator!$F$18) | AB2: =IF(Calculator!$B$19="",9999,Calculator!$F$19) | AC2: =IF(Calculator!$B$20="",9999,Calculator!$F$20) | AD2: =IF(Calculator!$B$21="",9999,Calculator!$F$21) | AE2: =IF(Calculator!$B$22="",9999,Calculator!$F$22) | AF2: =IF(Calculator!$B$23="",9999,Calculator!$F$23) | AG2: =IF(Calculator!$B$24="",9999,Calculator!$F$24) | AH2: =IF(Calculator!$B$25="",9999,Calculator!$F$25) | AI2: =IF(Calculator!$B$26="",9999,Calculator!$F$26) | AJ2: =IF(Calculator!$B$27="",9999,Calculator!$F$27) | AK2: =IF(Calculator!$B$28="",9999,Calculator!$F$28)
A3: 0 | BD3: =Calculator!$C$11 | BE3: =Calculator!$C$12 | BF3: =Calculator!$C$13 | BG3: =Calculator!$C$14 | BH3: =Calculator!$C$15 | BI3: =Calculator!$C$16 | BJ3: =Calculator!$C$17 | BK3: =Calculator!$C$18 | BL3: =Calculator!$C$19 | BM3: =Calculator!$C$20 | BN3: =Calculator!$C$21 | BO3: =Calculator!$C$22 | BP3: =Calculator!$C$23 | BQ3: =Calculator!$C$24 | BR3: =Calculator!$C$25 | BS3: =Calculator!$C$26 | BT3: =Calculator!$C$27 | BU3: =Calculator!$C$28 | BV3: =SUM(B3:S3) | BW3: =SUM(T3:AK3) | BX3: 0 | BY3: =SUM(BD3:BU3) | BZ3: 0 | CA3: =IF(A3<=IF($CD$1=0,999,$CD$1),BY3,NA()) | CB3: =IF(A3<=IF($CD$1=0,999,$CD$1),A3,NA())
A4: 1 | B4: =BD3*(1+Calculator!$D$11/100/12) | C4: =BE3*(1+Calculator!$D$12/100/12) | D4: =BF3*(1+Calculator!$D$13/100/12) | E4: =BG3*(1+Calculator!$D$14/100/12) | F4: =BH3*(1+Calculator!$D$15/100/12) | G4: =BI3*(1+Calculator!$D$16/100/12) | H4: =BJ3*(1+Calculator!$D$17/100/12) | I4: =BK3*(1+Calculator!$D$18/100/12) | J4: =BL3*(1+Calculator!$D$19/100/12) | K4: =BM3*(1+Calculator!$D$20/100/12) | L4: =BN3*(1+Calculator!$D$21/100/12) | M4: =BO3*(1+Calculator!$D$22/100/12) | N4: =BP3*(1+Calculator!$D$23/100/12) | O4: =BQ3*(1+Calculator!$D$24/100/12) | P4: =BR3*(1+Calculator!$D$25/100/12) | Q4: =BS3*(1+Calculator!$D$26/100/12) | R4: =BT3*(1+Calculator!$D$27/100/12) | S4: =BU3*(1+Calculator!$D$28/100/12) | T4: =MAX(0,B4-Calculator!$E$11) | U4: =MAX(0,C4-Calculator!$E$12) | V4: =MAX(0,D4-Calculator!$E$13) | W4: =MAX(0,E4-Calculator!$E$14) | X4: =MAX(0,F4-Calculator!$E$15) | Y4: =MAX(0,G4-Calculator!$E$16) | Z4: =MAX(0,H4-Calculator!$E$17) | AA4: =MAX(0,I4-Calculator!$E$18) | AB4: =MAX(0,J4-Calculator!$E$19) | AC4: =MAX(0,K4-Calculator!$E$20) | AD4: =MAX(0,L4-Calculator!$E$21) | AE4: =MAX(0,M4-Calculator!$E$22) | AF4: =MAX(0,N4-Calculator!$E$23) | AG4: =MAX(0,O4-Calculator!$E$24) | AH4: =MAX(0,P4-Calculator!$E$25) | AI4: =MAX(0,Q4-Calculator!$E$26) | AJ4: =MAX(0,R4-Calculator!$E$27) | AK4: =MAX(0,S4-Calculator!$E$28) | AL4: =MAX(0,MIN(T4,BX4-SUMPRODUCT(($T$2:$AK$2<T$2)*($T4:$AK4)))) | AM4: =MAX(0,MIN(U4,BX4-SUMPRODUCT(($T$2:$AK$2<U$2)*($T4:$AK4)))) | AN4: =MAX(0,MIN(V4,BX4-SUMPRODUCT(($T$2:$AK$2<V$2)*($T4:$AK4)))) | AO4: =MAX(0,MIN(W4,BX4-SUMPRODUCT(($T$2:$AK$2<W$2)*($T4:$AK4)))) | AP4: =MAX(0,MIN(X4,BX4-SUMPRODUCT(($T$2:$AK$2<X$2)*($T4:$AK4)))) | AQ4: =MAX(0,MIN(Y4,BX4-SUMPRODUCT(($T$2:$AK$2<Y$2)*($T4:$AK4)))) | AR4: =MAX(0,MIN(Z4,BX4-SUMPRODUCT(($T$2:$AK$2<Z$2)*($T4:$AK4)))) | AS4: =MAX(0,MIN(AA4,BX4-SUMPRODUCT(($T$2:$AK$2<AA$2)*($T4:$AK4)))) | AT4: =MAX(0,MIN(AB4,BX4-SUMPRODUCT(($T$2:$AK$2<AB$2)*($T4:$AK4)))) | AU4: =MAX(0,MIN(AC4,BX4-SUMPRODUCT(($T$2:$AK$2<AC$2)*($T4:$AK4)))) | AV4: =MAX(0,MIN(AD4,BX4-SUMPRODUCT(($T$2:$AK$2<AD$2)*($T4:$AK4)))) | AW4: =MAX(0,MIN(AE4,BX4-SUMPRODUCT(($T$2:$AK$2<AE$2)*($T4:$AK4)))) | AX4: =MAX(0,MIN(AF4,BX4-SUMPRODUCT(($T$2:$AK$2<AF$2)*($T4:$AK4)))) | AY4: =MAX(0,MIN(AG4,BX4-SUMPRODUCT(($T$2:$AK$2<AG$2)*($T4:$AK4)))) | AZ4: =MAX(0,MIN(AH4,BX4-SUMPRODUCT(($T$2:$AK$2<AH$2)*($T4:$AK4)))) | BA4: =MAX(0,MIN(AI4,BX4-SUMPRODUCT(($T$2:$AK$2<AI$2)*($T4:$AK4)))) | BB4: =MAX(0,MIN(AJ4,BX4-SUMPRODUCT(($T$2:$AK$2<AJ$2)*($T4:$AK4)))) | BC4: =MAX(0,MIN(AK4,BX4-SUMPRODUCT(($T$2:$AK$2<AK$2)*($T4:$AK4)))) | BD4: =T4-AL4 | BE4: =U4-AM4 | BF4: =V4-AN4 | BG4: =W4-AO4 | BH4: =X4-AP4 | BI4: =Y4-AQ4 | BJ4: =Z4-AR4 | BK4: =AA4-AS4 | ... BU4: =AK4-BC4 | BV4: =SUM(B4:S4) | BW4: =SUM(T4:AK4) | BX4: =MAX(0,(SUM(Calculator!$E$11:$E$28)+Calculator!$C$6)-BV4+BW4) | BY4: =SUM(BD4:BU4) | BZ4: =BV4-BY3 | CA4: =IF(A4<=IF($CD$1=0,999,$CD$1),BY4,NA()) | CB4: =IF(A4<=IF($CD$1=0,999,$CD$1),A4,NA())
A5: 2 | B5: =BD4*(1+Calculator!$D$11/100/12) | C5: =BE4*(1+Calculator!$D$12/100/12) | D5: =BF4*(1+Calculator!$D$13/100/12) | E5: =BG4*(1+Calculator!$D$14/100/12) | F5: =BH4*(1+Calculator!$D$15/100/12) | G5: =BI4*(1+Calculator!$D$16/100/12) | H5: =BJ4*(1+Calculator!$D$17/100/12) | I5: =BK4*(1+Calculator!$D$18/100/12) | J5: =BL4*(1+Calculator!$D$19/100/12) | K5: =BM4*(1+Calculator!$D$20/100/12) | L5: =BN4*(1+Calculator!$D$21/100/12) | M5: =BO4*(1+Calculator!$D$22/100/12) | N5: =BP4*(1+Calculator!$D$23/100/12) | O5: =BQ4*(1+Calculator!$D$24/100/12) | P5: =BR4*(1+Calculator!$D$25/100/12) | Q5: =BS4*(1+Calculator!$D$26/100/12) | R5: =BT4*(1+Calculator!$D$27/100/12) | S5: =BU4*(1+Calculator!$D$28/100/12) | T5: =MAX(0,B5-Calculator!$E$11) | U5: =MAX(0,C5-Calculator!$E$12) | V5: =MAX(0,D5-Calculator!$E$13) | W5: =MAX(0,E5-Calculator!$E$14) | X5: =MAX(0,F5-Calculator!$E$15) | Y5: =MAX(0,G5-Calculator!$E$16) | Z5: =MAX(0,H5-Calculator!$E$17) | AA5: =MAX(0,I5-Calculator!$E$18) | AB5: =MAX(0,J5-Calculator!$E$19) | AC5: =MAX(0,K5-Calculator!$E$20) | AD5: =MAX(0,L5-Calculator!$E$21) | AE5: =MAX(0,M5-Calculator!$E$22) | AF5: =MAX(0,N5-Calculator!$E$23) | AG5: =MAX(0,O5-Calculator!$E$24) | AH5: =MAX(0,P5-Calculator!$E$25) | AI5: =MAX(0,Q5-Calculator!$E$26) | AJ5: =MAX(0,R5-Calculator!$E$27) | AK5: =MAX(0,S5-Calculator!$E$28) | AL5: =MAX(0,MIN(T5,BX5-SUMPRODUCT(($T$2:$AK$2<T$2)*($T5:$AK5)))) | AM5: =MAX(0,MIN(U5,BX5-SUMPRODUCT(($T$2:$AK$2<U$2)*($T5:$AK5)))) | AN5: =MAX(0,MIN(V5,BX5-SUMPRODUCT(($T$2:$AK$2<V$2)*($T5:$AK5)))) | AO5: =MAX(0,MIN(W5,BX5-SUMPRODUCT(($T$2:$AK$2<W$2)*($T5:$AK5)))) | AP5: =MAX(0,MIN(X5,BX5-SUMPRODUCT(($T$2:$AK$2<X$2)*($T5:$AK5)))) | AQ5: =MAX(0,MIN(Y5,BX5-SUMPRODUCT(($T$2:$AK$2<Y$2)*($T5:$AK5)))) | AR5: =MAX(0,MIN(Z5,BX5-SUMPRODUCT(($T$2:$AK$2<Z$2)*($T5:$AK5)))) | AS5: =MAX(0,MIN(AA5,BX5-SUMPRODUCT(($T$2:$AK$2<AA$2)*($T5:$AK5)))) | AT5: =MAX(0,MIN(AB5,BX5-SUMPRODUCT(($T$2:$AK$2<AB$2)*($T5:$AK5)))) | AU5: =MAX(0,MIN(AC5,BX5-SUMPRODUCT(($T$2:$AK$2<AC$2)*($T5:$AK5)))) | AV5: =MAX(0,MIN(AD5,BX5-SUMPRODUCT(($T$2:$AK$2<AD$2)*($T5:$AK5)))) | AW5: =MAX(0,MIN(AE5,BX5-SUMPRODUCT(($T$2:$AK$2<AE$2)*($T5:$AK5)))) | AX5: =MAX(0,MIN(AF5,BX5-SUMPRODUCT(($T$2:$AK$2<AF$2)*($T5:$AK5)))) | AY5: =MAX(0,MIN(AG5,BX5-SUMPRODUCT(($T$2:$AK$2<AG$2)*($T5:$AK5)))) | AZ5: =MAX(0,MIN(AH5,BX5-SUMPRODUCT(($T$2:$AK$2<AH$2)*($T5:$AK5)))) | BA5: =MAX(0,MIN(AI5,BX5-SUMPRODUCT(($T$2:$AK$2<AI$2)*($T5:$AK5)))) | BB5: =MAX(0,MIN(AJ5,BX5-SUMPRODUCT(($T$2:$AK$2<AJ$2)*($T5:$AK5)))) | BC5: =MAX(0,MIN(AK5,BX5-SUMPRODUCT(($T$2:$AK$2<AK$2)*($T5:$AK5)))) | BD5: =T5-AL5 | BE5: =U5-AM5 | BF5: =V5-AN5 | BG5: =W5-AO5 | BH5: =X5-AP5 | BI5: =Y5-AQ5 | BJ5: =Z5-AR5 | BK5: =AA5-AS5 | ... BU5: =AK5-BC5 | BV5: =SUM(B5:S5) | BW5: =SUM(T5:AK5) | BX5: =MAX(0,(SUM(Calculator!$E$11:$E$28)+Calculator!$C$6)-BV5+BW5) | BY5: =SUM(BD5:BU5) | BZ5: =BV5-BY4 | CA5: =IF(A5<=IF($CD$1=0,999,$CD$1),BY5,NA()) | CB5: =IF(A5<=IF($CD$1=0,999,$CD$1),A5,NA())
A6: 3 | B6: =BD5*(1+Calculator!$D$11/100/12) | C6: =BE5*(1+Calculator!$D$12/100/12) | D6: =BF5*(1+Calculator!$D$13/100/12) | E6: =BG5*(1+Calculator!$D$14/100/12) | F6: =BH5*(1+Calculator!$D$15/100/12) | G6: =BI5*(1+Calculator!$D$16/100/12) | H6: =BJ5*(1+Calculator!$D$17/100/12) | I6: =BK5*(1+Calculator!$D$18/100/12) | J6: =BL5*(1+Calculator!$D$19/100/12) | K6: =BM5*(1+Calculator!$D$20/100/12) | L6: =BN5*(1+Calculator!$D$21/100/12) | M6: =BO5*(1+Calculator!$D$22/100/12) | N6: =BP5*(1+Calculator!$D$23/100/12) | O6: =BQ5*(1+Calculator!$D$24/100/12) | P6: =BR5*(1+Calculator!$D$25/100/12) | Q6: =BS5*(1+Calculator!$D$26/100/12) | R6: =BT5*(1+Calculator!$D$27/100/12) | S6: =BU5*(1+Calculator!$D$28/100/12) | T6: =MAX(0,B6-Calculator!$E$11) | U6: =MAX(0,C6-Calculator!$E$12) | V6: =MAX(0,D6-Calculator!$E$13) | W6: =MAX(0,E6-Calculator!$E$14) | X6: =MAX(0,F6-Calculator!$E$15) | Y6: =MAX(0,G6-Calculator!$E$16) | Z6: =MAX(0,H6-Calculator!$E$17) | AA6: =MAX(0,I6-Calculator!$E$18) | AB6: =MAX(0,J6-Calculator!$E$19) | AC6: =MAX(0,K6-Calculator!$E$20) | AD6: =MAX(0,L6-Calculator!$E$21) | AE6: =MAX(0,M6-Calculator!$E$22) | AF6: =MAX(0,N6-Calculator!$E$23) | AG6: =MAX(0,O6-Calculator!$E$24) | AH6: =MAX(0,P6-Calculator!$E$25) | AI6: =MAX(0,Q6-Calculator!$E$26) | AJ6: =MAX(0,R6-Calculator!$E$27) | AK6: =MAX(0,S6-Calculator!$E$28) | AL6: =MAX(0,MIN(T6,BX6-SUMPRODUCT(($T$2:$AK$2<T$2)*($T6:$AK6)))) | AM6: =MAX(0,MIN(U6,BX6-SUMPRODUCT(($T$2:$AK$2<U$2)*($T6:$AK6)))) | AN6: =MAX(0,MIN(V6,BX6-SUMPRODUCT(($T$2:$AK$2<V$2)*($T6:$AK6)))) | AO6: =MAX(0,MIN(W6,BX6-SUMPRODUCT(($T$2:$AK$2<W$2)*($T6:$AK6)))) | AP6: =MAX(0,MIN(X6,BX6-SUMPRODUCT(($T$2:$AK$2<X$2)*($T6:$AK6)))) | AQ6: =MAX(0,MIN(Y6,BX6-SUMPRODUCT(($T$2:$AK$2<Y$2)*($T6:$AK6)))) | AR6: =MAX(0,MIN(Z6,BX6-SUMPRODUCT(($T$2:$AK$2<Z$2)*($T6:$AK6)))) | AS6: =MAX(0,MIN(AA6,BX6-SUMPRODUCT(($T$2:$AK$2<AA$2)*($T6:$AK6)))) | AT6: =MAX(0,MIN(AB6,BX6-SUMPRODUCT(($T$2:$AK$2<AB$2)*($T6:$AK6)))) | AU6: =MAX(0,MIN(AC6,BX6-SUMPRODUCT(($T$2:$AK$2<AC$2)*($T6:$AK6)))) | AV6: =MAX(0,MIN(AD6,BX6-SUMPRODUCT(($T$2:$AK$2<AD$2)*($T6:$AK6)))) | AW6: =MAX(0,MIN(AE6,BX6-SUMPRODUCT(($T$2:$AK$2<AE$2)*($T6:$AK6)))) | AX6: =MAX(0,MIN(AF6,BX6-SUMPRODUCT(($T$2:$AK$2<AF$2)*($T6:$AK6)))) | AY6: =MAX(0,MIN(AG6,BX6-SUMPRODUCT(($T$2:$AK$2<AG$2)*($T6:$AK6)))) | AZ6: =MAX(0,MIN(AH6,BX6-SUMPRODUCT(($T$2:$AK$2<AH$2)*($T6:$AK6)))) | BA6: =MAX(0,MIN(AI6,BX6-SUMPRODUCT(($T$2:$AK$2<AI$2)*($T6:$AK6)))) | BB6: =MAX(0,MIN(AJ6,BX6-SUMPRODUCT(($T$2:$AK$2<AJ$2)*($T6:$AK6)))) | BC6: =MAX(0,MIN(AK6,BX6-SUMPRODUCT(($T$2:$AK$2<AK$2)*($T6:$AK6)))) | BD6: =T6-AL6 | BE6: =U6-AM6 | BF6: =V6-AN6 | BG6: =W6-AO6 | BH6: =X6-AP6 | BI6: =Y6-AQ6 | BJ6: =Z6-AR6 | BK6: =AA6-AS6 | ... BU6: =AK6-BC6 | BV6: =SUM(B6:S6) | BW6: =SUM(T6:AK6) | BX6: =MAX(0,(SUM(Calculator!$E$11:$E$28)+Calculator!$C$6)-BV6+BW6) | BY6: =SUM(BD6:BU6) | BZ6: =BV6-BY5 | CA6: =IF(A6<=IF($CD$1=0,999,$CD$1),BY6,NA()) | CB6: =IF(A6<=IF($CD$1=0,999,$CD$1),A6,NA())
A7: 4 | B7: =BD6*(1+Calculator!$D$11/100/12) | C7: =BE6*(1+Calculator!$D$12/100/12) | D7: =BF6*(1+Calculator!$D$13/100/12) | E7: =BG6*(1+Calculator!$D$14/100/12) | F7: =BH6*(1+Calculator!$D$15/100/12) | G7: =BI6*(1+Calculator!$D$16/100/12) | H7: =BJ6*(1+Calculator!$D$17/100/12) | I7: =BK6*(1+Calculator!$D$18/100/12) | J7: =BL6*(1+Calculator!$D$19/100/12) | K7: =BM6*(1+Calculator!$D$20/100/12) | L7: =BN6*(1+Calculator!$D$21/100/12) | M7: =BO6*(1+Calculator!$D$22/100/12) | N7: =BP6*(1+Calculator!$D$23/100/12) | O7: =BQ6*(1+Calculator!$D$24/100/12) | P7: =BR6*(1+Calculator!$D$25/100/12) | Q7: =BS6*(1+Calculator!$D$26/100/12) | R7: =BT6*(1+Calculator!$D$27/100/12) | S7: =BU6*(1+Calculator!$D$28/100/12) | T7: =MAX(0,B7-Calculator!$E$11) | U7: =MAX(0,C7-Calculator!$E$12) | V7: =MAX(0,D7-Calculator!$E$13) | W7: =MAX(0,E7-Calculator!$E$14) | X7: =MAX(0,F7-Calculator!$E$15) | Y7: =MAX(0,G7-Calculator!$E$16) | Z7: =MAX(0,H7-Calculator!$E$17) | AA7: =MAX(0,I7-Calculator!$E$18) | AB7: =MAX(0,J7-Calculator!$E$19) | AC7: =MAX(0,K7-Calculator!$E$20) | AD7: =MAX(0,L7-Calculator!$E$21) | AE7: =MAX(0,M7-Calculator!$E$22) | AF7: =MAX(0,N7-Calculator!$E$23) | AG7: =MAX(0,O7-Calculator!$E$24) | AH7: =MAX(0,P7-Calculator!$E$25) | AI7: =MAX(0,Q7-Calculator!$E$26) | AJ7: =MAX(0,R7-Calculator!$E$27) | AK7: =MAX(0,S7-Calculator!$E$28) | AL7: =MAX(0,MIN(T7,BX7-SUMPRODUCT(($T$2:$AK$2<T$2)*($T7:$AK7)))) | AM7: =MAX(0,MIN(U7,BX7-SUMPRODUCT(($T$2:$AK$2<U$2)*($T7:$AK7)))) | AN7: =MAX(0,MIN(V7,BX7-SUMPRODUCT(($T$2:$AK$2<V$2)*($T7:$AK7)))) | AO7: =MAX(0,MIN(W7,BX7-SUMPRODUCT(($T$2:$AK$2<W$2)*($T7:$AK7)))) | AP7: =MAX(0,MIN(X7,BX7-SUMPRODUCT(($T$2:$AK$2<X$2)*($T7:$AK7)))) | AQ7: =MAX(0,MIN(Y7,BX7-SUMPRODUCT(($T$2:$AK$2<Y$2)*($T7:$AK7)))) | AR7: =MAX(0,MIN(Z7,BX7-SUMPRODUCT(($T$2:$AK$2<Z$2)*($T7:$AK7)))) | AS7: =MAX(0,MIN(AA7,BX7-SUMPRODUCT(($T$2:$AK$2<AA$2)*($T7:$AK7)))) | AT7: =MAX(0,MIN(AB7,BX7-SUMPRODUCT(($T$2:$AK$2<AB$2)*($T7:$AK7)))) | AU7: =MAX(0,MIN(AC7,BX7-SUMPRODUCT(($T$2:$AK$2<AC$2)*($T7:$AK7)))) | AV7: =MAX(0,MIN(AD7,BX7-SUMPRODUCT(($T$2:$AK$2<AD$2)*($T7:$AK7)))) | AW7: =MAX(0,MIN(AE7,BX7-SUMPRODUCT(($T$2:$AK$2<AE$2)*($T7:$AK7)))) | AX7: =MAX(0,MIN(AF7,BX7-SUMPRODUCT(($T$2:$AK$2<AF$2)*($T7:$AK7)))) | AY7: =MAX(0,MIN(AG7,BX7-SUMPRODUCT(($T$2:$AK$2<AG$2)*($T7:$AK7)))) | AZ7: =MAX(0,MIN(AH7,BX7-SUMPRODUCT(($T$2:$AK$2<AH$2)*($T7:$AK7)))) | BA7: =MAX(0,MIN(AI7,BX7-SUMPRODUCT(($T$2:$AK$2<AI$2)*($T7:$AK7)))) | BB7: =MAX(0,MIN(AJ7,BX7-SUMPRODUCT(($T$2:$AK$2<AJ$2)*($T7:$AK7)))) | BC7: =MAX(0,MIN(AK7,BX7-SUMPRODUCT(($T$2:$AK$2<AK$2)*($T7:$AK7)))) | BD7: =T7-AL7 | BE7: =U7-AM7 | BF7: =V7-AN7 | BG7: =W7-AO7 | BH7: =X7-AP7 | BI7: =Y7-AQ7 | BJ7: =Z7-AR7 | BK7: =AA7-AS7 | ... BU7: =AK7-BC7 | BV7: =SUM(B7:S7) | BW7: =SUM(T7:AK7) | BX7: =MAX(0,(SUM(Calculator!$E$11:$E$28)+Calculator!$C$6)-BV7+BW7) | BY7: =SUM(BD7:BU7) | BZ7: =BV7-BY6 | CA7: =IF(A7<=IF($CD$1=0,999,$CD$1),BY7,NA()) | CB7: =IF(A7<=IF($CD$1=0,999,$CD$1),A7,NA())
A8: 5 | B8: =BD7*(1+Calculator!$D$11/100/12) | C8: =BE7*(1+Calculator!$D$12/100/12) | D8: =BF7*(1+Calculator!$D$13/100/12) | E8: =BG7*(1+Calculator!$D$14/100/12) | F8: =BH7*(1+Calculator!$D$15/100/12) | G8: =BI7*(1+Calculator!$D$16/100/12) | H8: =BJ7*(1+Calculator!$D$17/100/12) | I8: =BK7*(1+Calculator!$D$18/100/12) | J8: =BL7*(1+Calculator!$D$19/100/12) | K8: =BM7*(1+Calculator!$D$20/100/12) | L8: =BN7*(1+Calculator!$D$21/100/12) | M8: =BO7*(1+Calculator!$D$22/100/12) | N8: =BP7*(1+Calculator!$D$23/100/12) | O8: =BQ7*(1+Calculator!$D$24/100/12) | P8: =BR7*(1+Calculator!$D$25/100/12) | Q8: =BS7*(1+Calculator!$D$26/100/12) | R8: =BT7*(1+Calculator!$D$27/100/12) | S8: =BU7*(1+Calculator!$D$28/100/12) | T8: =MAX(0,B8-Calculator!$E$11) | U8: =MAX(0,C8-Calculator!$E$12) | V8: =MAX(0,D8-Calculator!$E$13) | W8: =MAX(0,E8-Calculator!$E$14) | X8: =MAX(0,F8-Calculator!$E$15) | Y8: =MAX(0,G8-Calculator!$E$16) | Z8: =MAX(0,H8-Calculator!$E$17) | AA8: =MAX(0,I8-Calculator!$E$18) | AB8: =MAX(0,J8-Calculator!$E$19) | AC8: =MAX(0,K8-Calculator!$E$20) | AD8: =MAX(0,L8-Calculator!$E$21) | AE8: =MAX(0,M8-Calculator!$E$22) | AF8: =MAX(0,N8-Calculator!$E$23) | AG8: =MAX(0,O8-Calculator!$E$24) | AH8: =MAX(0,P8-Calculator!$E$25) | AI8: =MAX(0,Q8-Calculator!$E$26) | AJ8: =MAX(0,R8-Calculator!$E$27) | AK8: =MAX(0,S8-Calculator!$E$28) | AL8: =MAX(0,MIN(T8,BX8-SUMPRODUCT(($T$2:$AK$2<T$2)*($T8:$AK8)))) | AM8: =MAX(0,MIN(U8,BX8-SUMPRODUCT(($T$2:$AK$2<U$2)*($T8:$AK8)))) | AN8: =MAX(0,MIN(V8,BX8-SUMPRODUCT(($T$2:$AK$2<V$2)*($T8:$AK8)))) | AO8: =MAX(0,MIN(W8,BX8-SUMPRODUCT(($T$2:$AK$2<W$2)*($T8:$AK8)))) | AP8: =MAX(0,MIN(X8,BX8-SUMPRODUCT(($T$2:$AK$2<X$2)*($T8:$AK8)))) | AQ8: =MAX(0,MIN(Y8,BX8-SUMPRODUCT(($T$2:$AK$2<Y$2)*($T8:$AK8)))) | AR8: =MAX(0,MIN(Z8,BX8-SUMPRODUCT(($T$2:$AK$2<Z$2)*($T8:$AK8)))) | AS8: =MAX(0,MIN(AA8,BX8-SUMPRODUCT(($T$2:$AK$2<AA$2)*($T8:$AK8)))) | AT8: =MAX(0,MIN(AB8,BX8-SUMPRODUCT(($T$2:$AK$2<AB$2)*($T8:$AK8)))) | AU8: =MAX(0,MIN(AC8,BX8-SUMPRODUCT(($T$2:$AK$2<AC$2)*($T8:$AK8)))) | AV8: =MAX(0,MIN(AD8,BX8-SUMPRODUCT(($T$2:$AK$2<AD$2)*($T8:$AK8)))) | AW8: =MAX(0,MIN(AE8,BX8-SUMPRODUCT(($T$2:$AK$2<AE$2)*($T8:$AK8)))) | AX8: =MAX(0,MIN(AF8,BX8-SUMPRODUCT(($T$2:$AK$2<AF$2)*($T8:$AK8)))) | AY8: =MAX(0,MIN(AG8,BX8-SUMPRODUCT(($T$2:$AK$2<AG$2)*($T8:$AK8)))) | AZ8: =MAX(0,MIN(AH8,BX8-SUMPRODUCT(($T$2:$AK$2<AH$2)*($T8:$AK8)))) | BA8: =MAX(0,MIN(AI8,BX8-SUMPRODUCT(($T$2:$AK$2<AI$2)*($T8:$AK8)))) | BB8: =MAX(0,MIN(AJ8,BX8-SUMPRODUCT(($T$2:$AK$2<AJ$2)*($T8:$AK8)))) | BC8: =MAX(0,MIN(AK8,BX8-SUMPRODUCT(($T$2:$AK$2<AK$2)*($T8:$AK8)))) | BD8: =T8-AL8 | BE8: =U8-AM8 | BF8: =V8-AN8 | BG8: =W8-AO8 | BH8: =X8-AP8 | BI8: =Y8-AQ8 | BJ8: =Z8-AR8 | BK8: =AA8-AS8 | ... BU8: =AK8-BC8 | BV8: =SUM(B8:S8) | BW8: =SUM(T8:AK8) | BX8: =MAX(0,(SUM(Calculator!$E$11:$E$28)+Calculator!$C$6)-BV8+BW8) | BY8: =SUM(BD8:BU8) | BZ8: =BV8-BY7 | CA8: =IF(A8<=IF($CD$1=0,999,$CD$1),BY8,NA()) | CB8: =IF(A8<=IF($CD$1=0,999,$CD$1),A8,NA())
A9: 6 | B9: =BD8*(1+Calculator!$D$11/100/12) | C9: =BE8*(1+Calculator!$D$12/100/12) | D9: =BF8*(1+Calculator!$D$13/100/12) | E9: =BG8*(1+Calculator!$D$14/100/12) | F9: =BH8*(1+Calculator!$D$15/100/12) | G9: =BI8*(1+Calculator!$D$16/100/12) | H9: =BJ8*(1+Calculator!$D$17/100/12) | I9: =BK8*(1+Calculator!$D$18/100/12) | J9: =BL8*(1+Calculator!$D$19/100/12) | K9: =BM8*(1+Calculator!$D$20/100/12) | L9: =BN8*(1+Calculator!$D$21/100/12) | M9: =BO8*(1+Calculator!$D$22/100/12) | N9: =BP8*(1+Calculator!$D$23/100/12) | O9: =BQ8*(1+Calculator!$D$24/100/12) | P9: =BR8*(1+Calculator!$D$25/100/12) | Q9: =BS8*(1+Calculator!$D$26/100/12) | R9: =BT8*(1+Calculator!$D$27/100/12) | S9: =BU8*(1+Calculator!$D$28/100/12) | T9: =MAX(0,B9-Calculator!$E$11) | U9: =MAX(0,C9-Calculator!$E$12) | V9: =MAX(0,D9-Calculator!$E$13) | W9: =MAX(0,E9-Calculator!$E$14) | X9: =MAX(0,F9-Calculator!$E$15) | Y9: =MAX(0,G9-Calculator!$E$16) | Z9: =MAX(0,H9-Calculator!$E$17) | AA9: =MAX(0,I9-Calculator!$E$18) | AB9: =MAX(0,J9-Calculator!$E$19) | AC9: =MAX(0,K9-Calculator!$E$20) | AD9: =MAX(0,L9-Calculator!$E$21) | AE9: =MAX(0,M9-Calculator!$E$22) | AF9: =MAX(0,N9-Calculator!$E$23) | AG9: =MAX(0,O9-Calculator!$E$24) | AH9: =MAX(0,P9-Calculator!$E$25) | AI9: =MAX(0,Q9-Calculator!$E$26) | AJ9: =MAX(0,R9-Calculator!$E$27) | AK9: =MAX(0,S9-Calculator!$E$28) | AL9: =MAX(0,MIN(T9,BX9-SUMPRODUCT(($T$2:$AK$2<T$2)*($T9:$AK9)))) | AM9: =MAX(0,MIN(U9,BX9-SUMPRODUCT(($T$2:$AK$2<U$2)*($T9:$AK9)))) | AN9: =MAX(0,MIN(V9,BX9-SUMPRODUCT(($T$2:$AK$2<V$2)*($T9:$AK9)))) | AO9: =MAX(0,MIN(W9,BX9-SUMPRODUCT(($T$2:$AK$2<W$2)*($T9:$AK9)))) | AP9: =MAX(0,MIN(X9,BX9-SUMPRODUCT(($T$2:$AK$2<X$2)*($T9:$AK9)))) | AQ9: =MAX(0,MIN(Y9,BX9-SUMPRODUCT(($T$2:$AK$2<Y$2)*($T9:$AK9)))) | AR9: =MAX(0,MIN(Z9,BX9-SUMPRODUCT(($T$2:$AK$2<Z$2)*($T9:$AK9)))) | AS9: =MAX(0,MIN(AA9,BX9-SUMPRODUCT(($T$2:$AK$2<AA$2)*($T9:$AK9)))) | AT9: =MAX(0,MIN(AB9,BX9-SUMPRODUCT(($T$2:$AK$2<AB$2)*($T9:$AK9)))) | AU9: =MAX(0,MIN(AC9,BX9-SUMPRODUCT(($T$2:$AK$2<AC$2)*($T9:$AK9)))) | AV9: =MAX(0,MIN(AD9,BX9-SUMPRODUCT(($T$2:$AK$2<AD$2)*($T9:$AK9)))) | AW9: =MAX(0,MIN(AE9,BX9-SUMPRODUCT(($T$2:$AK$2<AE$2)*($T9:$AK9)))) | AX9: =MAX(0,MIN(AF9,BX9-SUMPRODUCT(($T$2:$AK$2<AF$2)*($T9:$AK9)))) | AY9: =MAX(0,MIN(AG9,BX9-SUMPRODUCT(($T$2:$AK$2<AG$2)*($T9:$AK9)))) | AZ9: =MAX(0,MIN(AH9,BX9-SUMPRODUCT(($T$2:$AK$2<AH$2)*($T9:$AK9)))) | BA9: =MAX(0,MIN(AI9,BX9-SUMPRODUCT(($T$2:$AK$2<AI$2)*($T9:$AK9)))) | BB9: =MAX(0,MIN(AJ9,BX9-SUMPRODUCT(($T$2:$AK$2<AJ$2)*($T9:$AK9)))) | BC9: =MAX(0,MIN(AK9,BX9-SUMPRODUCT(($T$2:$AK$2<AK$2)*($T9:$AK9)))) | BD9: =T9-AL9 | BE9: =U9-AM9 | BF9: =V9-AN9 | BG9: =W9-AO9 | BH9: =X9-AP9 | BI9: =Y9-AQ9 | BJ9: =Z9-AR9 | BK9: =AA9-AS9 | ... BU9: =AK9-BC9 | BV9: =SUM(B9:S9) | BW9: =SUM(T9:AK9) | BX9: =MAX(0,(SUM(Calculator!$E$11:$E$28)+Calculator!$C$6)-BV9+BW9) | BY9: =SUM(BD9:BU9) | BZ9: =BV9-BY8 | CA9: =IF(A9<=IF($CD$1=0,999,$CD$1),BY9,NA()) | CB9: =IF(A9<=IF($CD$1=0,999,$CD$1),A9,NA())
A10: 7 | B10: =BD9*(1+Calculator!$D$11/100/12) | C10: =BE9*(1+Calculator!$D$12/100/12) | D10: =BF9*(1+Calculator!$D$13/100/12) | E10: =BG9*(1+Calculator!$D$14/100/12) | F10: =BH9*(1+Calculator!$D$15/100/12) | G10: =BI9*(1+Calculator!$D$16/100/12) | H10: =BJ9*(1+Calculator!$D$17/100/12) | I10: =BK9*(1+Calculator!$D$18/100/12) | J10: =BL9*(1+Calculator!$D$19/100/12) | K10: =BM9*(1+Calculator!$D$20/100/12) | L10: =BN9*(1+Calculator!$D$21/100/12) | M10: =BO9*(1+Calculator!$D$22/100/12) | N10: =BP9*(1+Calculator!$D$23/100/12) | O10: =BQ9*(1+Calculator!$D$24/100/12) | P10: =BR9*(1+Calculator!$D$25/100/12) | Q10: =BS9*(1+Calculator!$D$26/100/12) | R10: =BT9*(1+Calculator!$D$27/100/12) | S10: =BU9*(1+Calculator!$D$28/100/12) | T10: =MAX(0,B10-Calculator!$E$11) | U10: =MAX(0,C10-Calculator!$E$12) | V10: =MAX(0,D10-Calculator!$E$13) | W10: =MAX(0,E10-Calculator!$E$14) | X10: =MAX(0,F10-Calculator!$E$15) | Y10: =MAX(0,G10-Calculator!$E$16) | Z10: =MAX(0,H10-Calculator!$E$17) | AA10: =MAX(0,I10-Calculator!$E$18) | AB10: =MAX(0,J10-Calculator!$E$19) | AC10: =MAX(0,K10-Calculator!$E$20) | AD10: =MAX(0,L10-Calculator!$E$21) | AE10: =MAX(0,M10-Calculator!$E$22) | AF10: =MAX(0,N10-Calculator!$E$23) | AG10: =MAX(0,O10-Calculator!$E$24) | AH10: =MAX(0,P10-Calculator!$E$25) | AI10: =MAX(0,Q10-Calculator!$E$26) | AJ10: =MAX(0,R10-Calculator!$E$27) | AK10: =MAX(0,S10-Calculator!$E$28) | AL10: =MAX(0,MIN(T10,BX10-SUMPRODUCT(($T$2:$AK$2<T$2)*($T10:$AK10)))) | AM10: =MAX(0,MIN(U10,BX10-SUMPRODUCT(($T$2:$AK$2<U$2)*($T10:$AK10)))) | AN10: =MAX(0,MIN(V10,BX10-SUMPRODUCT(($T$2:$AK$2<V$2)*($T10:$AK10)))) | AO10: =MAX(0,MIN(W10,BX10-SUMPRODUCT(($T$2:$AK$2<W$2)*($T10:$AK10)))) | AP10: =MAX(0,MIN(X10,BX10-SUMPRODUCT(($T$2:$AK$2<X$2)*($T10:$AK10)))) | AQ10: =MAX(0,MIN(Y10,BX10-SUMPRODUCT(($T$2:$AK$2<Y$2)*($T10:$AK10)))) | AR10: =MAX(0,MIN(Z10,BX10-SUMPRODUCT(($T$2:$AK$2<Z$2)*($T10:$AK10)))) | AS10: =MAX(0,MIN(AA10,BX10-SUMPRODUCT(($T$2:$AK$2<AA$2)*($T10:$AK10)))) | AT10: =MAX(0,MIN(AB10,BX10-SUMPRODUCT(($T$2:$AK$2<AB$2)*($T10:$AK10)))) | AU10: =MAX(0,MIN(AC10,BX10-SUMPRODUCT(($T$2:$AK$2<AC$2)*($T10:$AK10)))) | AV10: =MAX(0,MIN(AD10,BX10-SUMPRODUCT(($T$2:$AK$2<AD$2)*($T10:$AK10)))) | AW10: =MAX(0,MIN(AE10,BX10-SUMPRODUCT(($T$2:$AK$2<AE$2)*($T10:$AK10)))) | AX10: =MAX(0,MIN(AF10,BX10-SUMPRODUCT(($T$2:$AK$2<AF$2)*($T10:$AK10)))) | AY10: =MAX(0,MIN(AG10,BX10-SUMPRODUCT(($T$2:$AK$2<AG$2)*($T10:$AK10)))) | AZ10: =MAX(0,MIN(AH10,BX10-SUMPRODUCT(($T$2:$AK$2<AH$2)*($T10:$AK10)))) | BA10: =MAX(0,MIN(AI10,BX10-SUMPRODUCT(($T$2:$AK$2<AI$2)*($T10:$AK10)))) | BB10: =MAX(0,MIN(AJ10,BX10-SUMPRODUCT(($T$2:$AK$2<AJ$2)*($T10:$AK10)))) | BC10: =MAX(0,MIN(AK10,BX10-SUMPRODUCT(($T$2:$AK$2<AK$2)*($T10:$AK10)))) | BD10: =T10-AL10 | BE10: =U10-AM10 | BF10: =V10-AN10 | BG10: =W10-AO10 | BH10: =X10-AP10 | BI10: =Y10-AQ10 | BJ10: =Z10-AR10 | BK10: =AA10-AS10 | ... BU10: =AK10-BC10 | BV10: =SUM(B10:S10) | BW10: =SUM(T10:AK10) | BX10: =MAX(0,(SUM(Calculator!$E$11:$E$28)+Calculator!$C$6)-BV10+BW10) | BY10: =SUM(BD10:BU10) | BZ10: =BV10-BY9 | CA10: =IF(A10<=IF($CD$1=0,999,$CD$1),BY10,NA()) | CB10: =IF(A10<=IF($CD$1=0,999,$CD$1),A10,NA())
A11: 8 | B11: =BD10*(1+Calculator!$D$11/100/12) | C11: =BE10*(1+Calculator!$D$12/100/12) | D11: =BF10*(1+Calculator!$D$13/100/12) | E11: =BG10*(1+Calculator!$D$14/100/12) | F11: =BH10*(1+Calculator!$D$15/100/12) | G11: =BI10*(1+Calculator!$D$16/100/12) | H11: =BJ10*(1+Calculator!$D$17/100/12) | I11: =BK10*(1+Calculator!$D$18/100/12) | J11: =BL10*(1+Calculator!$D$19/100/12) | K11: =BM10*(1+Calculator!$D$20/100/12) | L11: =BN10*(1+Calculator!$D$21/100/12) | M11: =BO10*(1+Calculator!$D$22/100/12) | N11: =BP10*(1+Calculator!$D$23/100/12) | O11: =BQ10*(1+Calculator!$D$24/100/12) | P11: =BR10*(1+Calculator!$D$25/100/12) | Q11: =BS10*(1+Calculator!$D$26/100/12) | R11: =BT10*(1+Calculator!$D$27/100/12) | S11: =BU10*(1+Calculator!$D$28/100/12) | T11: =MAX(0,B11-Calculator!$E$11) | U11: =MAX(0,C11-Calculator!$E$12) | V11: =MAX(0,D11-Calculator!$E$13) | W11: =MAX(0,E11-Calculator!$E$14) | X11: =MAX(0,F11-Calculator!$E$15) | Y11: =MAX(0,G11-Calculator!$E$16) | Z11: =MAX(0,H11-Calculator!$E$17) | AA11: =MAX(0,I11-Calculator!$E$18) | AB11: =MAX(0,J11-Calculator!$E$19) | AC11: =MAX(0,K11-Calculator!$E$20) | AD11: =MAX(0,L11-Calculator!$E$21) | AE11: =MAX(0,M11-Calculator!$E$22) | AF11: =MAX(0,N11-Calculator!$E$23) | AG11: =MAX(0,O11-Calculator!$E$24) | AH11: =MAX(0,P11-Calculator!$E$25) | AI11: =MAX(0,Q11-Calculator!$E$26) | AJ11: =MAX(0,R11-Calculator!$E$27) | AK11: =MAX(0,S11-Calculator!$E$28) | AL11: =MAX(0,MIN(T11,BX11-SUMPRODUCT(($T$2:$AK$2<T$2)*($T11:$AK11)))) | AM11: =MAX(0,MIN(U11,BX11-SUMPRODUCT(($T$2:$AK$2<U$2)*($T11:$AK11)))) | AN11: =MAX(0,MIN(V11,BX11-SUMPRODUCT(($T$2:$AK$2<V$2)*($T11:$AK11)))) | AO11: =MAX(0,MIN(W11,BX11-SUMPRODUCT(($T$2:$AK$2<W$2)*($T11:$AK11)))) | AP11: =MAX(0,MIN(X11,BX11-SUMPRODUCT(($T$2:$AK$2<X$2)*($T11:$AK11)))) | AQ11: =MAX(0,MIN(Y11,BX11-SUMPRODUCT(($T$2:$AK$2<Y$2)*($T11:$AK11)))) | AR11: =MAX(0,MIN(Z11,BX11-SUMPRODUCT(($T$2:$AK$2<Z$2)*($T11:$AK11)))) | AS11: =MAX(0,MIN(AA11,BX11-SUMPRODUCT(($T$2:$AK$2<AA$2)*($T11:$AK11)))) | AT11: =MAX(0,MIN(AB11,BX11-SUMPRODUCT(($T$2:$AK$2<AB$2)*($T11:$AK11)))) | AU11: =MAX(0,MIN(AC11,BX11-SUMPRODUCT(($T$2:$AK$2<AC$2)*($T11:$AK11)))) | AV11: =MAX(0,MIN(AD11,BX11-SUMPRODUCT(($T$2:$AK$2<AD$2)*($T11:$AK11)))) | AW11: =MAX(0,MIN(AE11,BX11-SUMPRODUCT(($T$2:$AK$2<AE$2)*($T11:$AK11)))) | AX11: =MAX(0,MIN(AF11,BX11-SUMPRODUCT(($T$2:$AK$2<AF$2)*($T11:$AK11)))) | AY11: =MAX(0,MIN(AG11,BX11-SUMPRODUCT(($T$2:$AK$2<AG$2)*($T11:$AK11)))) | AZ11: =MAX(0,MIN(AH11,BX11-SUMPRODUCT(($T$2:$AK$2<AH$2)*($T11:$AK11)))) | BA11: =MAX(0,MIN(AI11,BX11-SUMPRODUCT(($T$2:$AK$2<AI$2)*($T11:$AK11)))) | BB11: =MAX(0,MIN(AJ11,BX11-SUMPRODUCT(($T$2:$AK$2<AJ$2)*($T11:$AK11)))) | BC11: =MAX(0,MIN(AK11,BX11-SUMPRODUCT(($T$2:$AK$2<AK$2)*($T11:$AK11)))) | BD11: =T11-AL11 | BE11: =U11-AM11 | BF11: =V11-AN11 | BG11: =W11-AO11 | BH11: =X11-AP11 | BI11: =Y11-AQ11 | BJ11: =Z11-AR11 | BK11: =AA11-AS11 | ... BU11: =AK11-BC11 | BV11: =SUM(B11:S11) | BW11: =SUM(T11:AK11) | BX11: =MAX(0,(SUM(Calculator!$E$11:$E$28)+Calculator!$C$6)-BV11+BW11) | BY11: =SUM(BD11:BU11) | BZ11: =BV11-BY10 | CA11: =IF(A11<=IF($CD$1=0,999,$CD$1),BY11,NA()) | CB11: =IF(A11<=IF($CD$1=0,999,$CD$1),A11,NA())
A12: 9 | B12: =BD11*(1+Calculator!$D$11/100/12) | C12: =BE11*(1+Calculator!$D$12/100/12) | D12: =BF11*(1+Calculator!$D$13/100/12) | E12: =BG11*(1+Calculator!$D$14/100/12) | F12: =BH11*(1+Calculator!$D$15/100/12) | G12: =BI11*(1+Calculator!$D$16/100/12) | H12: =BJ11*(1+Calculator!$D$17/100/12) | I12: =BK11*(1+Calculator!$D$18/100/12) | J12: =BL11*(1+Calculator!$D$19/100/12) | K12: =BM11*(1+Calculator!$D$20/100/12) | L12: =BN11*(1+Calculator!$D$21/100/12) | M12: =BO11*(1+Calculator!$D$22/100/12) | N12: =BP11*(1+Calculator!$D$23/100/12) | O12: =BQ11*(1+Calculator!$D$24/100/12) | P12: =BR11*(1+Calculator!$D$25/100/12) | Q12: =BS11*(1+Calculator!$D$26/100/12) | R12: =BT11*(1+Calculator!$D$27/100/12) | S12: =BU11*(1+Calculator!$D$28/100/12) | T12: =MAX(0,B12-Calculator!$E$11) | U12: =MAX(0,C12-Calculator!$E$12) | V12: =MAX(0,D12-Calculator!$E$13) | W12: =MAX(0,E12-Calculator!$E$14) | X12: =MAX(0,F12-Calculator!$E$15) | Y12: =MAX(0,G12-Calculator!$E$16) | Z12: =MAX(0,H12-Calculator!$E$17) | AA12: =MAX(0,I12-Calculator!$E$18) | AB12: =MAX(0,J12-Calculator!$E$19) | AC12: =MAX(0,K12-Calculator!$E$20) | AD12: =MAX(0,L12-Calculator!$E$21) | AE12: =MAX(0,M12-Calculator!$E$22) | AF12: =MAX(0,N12-Calculator!$E$23) | AG12: =MAX(0,O12-Calculator!$E$24) | AH12: =MAX(0,P12-Calculator!$E$25) | AI12: =MAX(0,Q12-Calculator!$E$26) | AJ12: =MAX(0,R12-Calculator!$E$27) | AK12: =MAX(0,S12-Calculator!$E$28) | AL12: =MAX(0,MIN(T12,BX12-SUMPRODUCT(($T$2:$AK$2<T$2)*($T12:$AK12)))) | AM12: =MAX(0,MIN(U12,BX12-SUMPRODUCT(($T$2:$AK$2<U$2)*($T12:$AK12)))) | AN12: =MAX(0,MIN(V12,BX12-SUMPRODUCT(($T$2:$AK$2<V$2)*($T12:$AK12)))) | AO12: =MAX(0,MIN(W12,BX12-SUMPRODUCT(($T$2:$AK$2<W$2)*($T12:$AK12)))) | AP12: =MAX(0,MIN(X12,BX12-SUMPRODUCT(($T$2:$AK$2<X$2)*($T12:$AK12)))) | AQ12: =MAX(0,MIN(Y12,BX12-SUMPRODUCT(($T$2:$AK$2<Y$2)*($T12:$AK12)))) | AR12: =MAX(0,MIN(Z12,BX12-SUMPRODUCT(($T$2:$AK$2<Z$2)*($T12:$AK12)))) | AS12: =MAX(0,MIN(AA12,BX12-SUMPRODUCT(($T$2:$AK$2<AA$2)*($T12:$AK12)))) | AT12: =MAX(0,MIN(AB12,BX12-SUMPRODUCT(($T$2:$AK$2<AB$2)*($T12:$AK12)))) | AU12: =MAX(0,MIN(AC12,BX12-SUMPRODUCT(($T$2:$AK$2<AC$2)*($T12:$AK12)))) | AV12: =MAX(0,MIN(AD12,BX12-SUMPRODUCT(($T$2:$AK$2<AD$2)*($T12:$AK12)))) | AW12: =MAX(0,MIN(AE12,BX12-SUMPRODUCT(($T$2:$AK$2<AE$2)*($T12:$AK12)))) | AX12: =MAX(0,MIN(AF12,BX12-SUMPRODUCT(($T$2:$AK$2<AF$2)*($T12:$AK12)))) | AY12: =MAX(0,MIN(AG12,BX12-SUMPRODUCT(($T$2:$AK$2<AG$2)*($T12:$AK12)))) | AZ12: =MAX(0,MIN(AH12,BX12-SUMPRODUCT(($T$2:$AK$2<AH$2)*($T12:$AK12)))) | BA12: =MAX(0,MIN(AI12,BX12-SUMPRODUCT(($T$2:$AK$2<AI$2)*($T12:$AK12)))) | BB12: =MAX(0,MIN(AJ12,BX12-SUMPRODUCT(($T$2:$AK$2<AJ$2)*($T12:$AK12)))) | BC12: =MAX(0,MIN(AK12,BX12-SUMPRODUCT(($T$2:$AK$2<AK$2)*($T12:$AK12)))) | BD12: =T12-AL12 | BE12: =U12-AM12 | BF12: =V12-AN12 | BG12: =W12-AO12 | BH12: =X12-AP12 | BI12: =Y12-AQ12 | BJ12: =Z12-AR12 | BK12: =AA12-AS12 | ... BU12: =AK12-BC12 | BV12: =SUM(B12:S12) | BW12: =SUM(T12:AK12) | BX12: =MAX(0,(SUM(Calculator!$E$11:$E$28)+Calculator!$C$6)-BV12+BW12) | BY12: =SUM(BD12:BU12) | BZ12: =BV12-BY11 | CA12: =IF(A12<=IF($CD$1=0,999,$CD$1),BY12,NA()) | CB12: =IF(A12<=IF($CD$1=0,999,$CD$1),A12,NA())
A13: 10 | B13: =BD12*(1+Calculator!$D$11/100/12) | C13: =BE12*(1+Calculator!$D$12/100/12) | D13: =BF12*(1+Calculator!$D$13/100/12) | E13: =BG12*(1+Calculator!$D$14/100/12) | F13: =BH12*(1+Calculator!$D$15/100/12) | G13: =BI12*(1+Calculator!$D$16/100/12) | H13: =BJ12*(1+Calculator!$D$17/100/12) | I13: =BK12*(1+Calculator!$D$18/100/12) | J13: =BL12*(1+Calculator!$D$19/100/12) | K13: =BM12*(1+Calculator!$D$20/100/12) | L13: =BN12*(1+Calculator!$D$21/100/12) | M13: =BO12*(1+Calculator!$D$22/100/12) | N13: =BP12*(1+Calculator!$D$23/100/12) | O13: =BQ12*(1+Calculator!$D$24/100/12) | P13: =BR12*(1+Calculator!$D$25/100/12) | Q13: =BS12*(1+Calculator!$D$26/100/12) | R13: =BT12*(1+Calculator!$D$27/100/12) | S13: =BU12*(1+Calculator!$D$28/100/12) | T13: =MAX(0,B13-Calculator!$E$11) | U13: =MAX(0,C13-Calculator!$E$12) | V13: =MAX(0,D13-Calculator!$E$13) | W13: =MAX(0,E13-Calculator!$E$14) | X13: =MAX(0,F13-Calculator!$E$15) | Y13: =MAX(0,G13-Calculator!$E$16) | Z13: =MAX(0,H13-Calculator!$E$17) | AA13: =MAX(0,I13-Calculator!$E$18) | AB13: =MAX(0,J13-Calculator!$E$19) | AC13: =MAX(0,K13-Calculator!$E$20) | AD13: =MAX(0,L13-Calculator!$E$21) | AE13: =MAX(0,M13-Calculator!$E$22) | AF13: =MAX(0,N13-Calculator!$E$23) | AG13: =MAX(0,O13-Calculator!$E$24) | AH13: =MAX(0,P13-Calculator!$E$25) | AI13: =MAX(0,Q13-Calculator!$E$26) | AJ13: =MAX(0,R13-Calculator!$E$27) | AK13: =MAX(0,S13-Calculator!$E$28) | AL13: =MAX(0,MIN(T13,BX13-SUMPRODUCT(($T$2:$AK$2<T$2)*($T13:$AK13)))) | AM13: =MAX(0,MIN(U13,BX13-SUMPRODUCT(($T$2:$AK$2<U$2)*($T13:$AK13)))) | AN13: =MAX(0,MIN(V13,BX13-SUMPRODUCT(($T$2:$AK$2<V$2)*($T13:$AK13)))) | AO13: =MAX(0,MIN(W13,BX13-SUMPRODUCT(($T$2:$AK$2<W$2)*($T13:$AK13)))) | AP13: =MAX(0,MIN(X13,BX13-SUMPRODUCT(($T$2:$AK$2<X$2)*($T13:$AK13)))) | AQ13: =MAX(0,MIN(Y13,BX13-SUMPRODUCT(($T$2:$AK$2<Y$2)*($T13:$AK13)))) | AR13: =MAX(0,MIN(Z13,BX13-SUMPRODUCT(($T$2:$AK$2<Z$2)*($T13:$AK13)))) | AS13: =MAX(0,MIN(AA13,BX13-SUMPRODUCT(($T$2:$AK$2<AA$2)*($T13:$AK13)))) | AT13: =MAX(0,MIN(AB13,BX13-SUMPRODUCT(($T$2:$AK$2<AB$2)*($T13:$AK13)))) | AU13: =MAX(0,MIN(AC13,BX13-SUMPRODUCT(($T$2:$AK$2<AC$2)*($T13:$AK13)))) | AV13: =MAX(0,MIN(AD13,BX13-SUMPRODUCT(($T$2:$AK$2<AD$2)*($T13:$AK13)))) | AW13: =MAX(0,MIN(AE13,BX13-SUMPRODUCT(($T$2:$AK$2<AE$2)*($T13:$AK13)))) | AX13: =MAX(0,MIN(AF13,BX13-SUMPRODUCT(($T$2:$AK$2<AF$2)*($T13:$AK13)))) | AY13: =MAX(0,MIN(AG13,BX13-SUMPRODUCT(($T$2:$AK$2<AG$2)*($T13:$AK13)))) | AZ13: =MAX(0,MIN(AH13,BX13-SUMPRODUCT(($T$2:$AK$2<AH$2)*($T13:$AK13)))) | BA13: =MAX(0,MIN(AI13,BX13-SUMPRODUCT(($T$2:$AK$2<AI$2)*($T13:$AK13)))) | BB13: =MAX(0,MIN(AJ13,BX13-SUMPRODUCT(($T$2:$AK$2<AJ$2)*($T13:$AK13)))) | BC13: =MAX(0,MIN(AK13,BX13-SUMPRODUCT(($T$2:$AK$2<AK$2)*($T13:$AK13)))) | BD13: =T13-AL13 | BE13: =U13-AM13 | BF13: =V13-AN13 | BG13: =W13-AO13 | BH13: =X13-AP13 | BI13: =Y13-AQ13 | BJ13: =Z13-AR13 | BK13: =AA13-AS13 | ... BU13: =AK13-BC13 | BV13: =SUM(B13:S13) | BW13: =SUM(T13:AK13) | BX13: =MAX(0,(SUM(Calculator!$E$11:$E$28)+Calculator!$C$6)-BV13+BW13) | BY13: =SUM(BD13:BU13) | BZ13: =BV13-BY12 | CA13: =IF(A13<=IF($CD$1=0,999,$CD$1),BY13,NA()) | CB13: =IF(A13<=IF($CD$1=0,999,$CD$1),A13,NA())
A14: 11 | B14: =BD13*(1+Calculator!$D$11/100/12) | C14: =BE13*(1+Calculator!$D$12/100/12) | D14: =BF13*(1+Calculator!$D$13/100/12) | E14: =BG13*(1+Calculator!$D$14/100/12) | F14: =BH13*(1+Calculator!$D$15/100/12) | G14: =BI13*(1+Calculator!$D$16/100/12) | H14: =BJ13*(1+Calculator!$D$17/100/12) | I14: =BK13*(1+Calculator!$D$18/100/12) | J14: =BL13*(1+Calculator!$D$19/100/12) | K14: =BM13*(1+Calculator!$D$20/100/12) | L14: =BN13*(1+Calculator!$D$21/100/12) | M14: =BO13*(1+Calculator!$D$22/100/12) | N14: =BP13*(1+Calculator!$D$23/100/12) | O14: =BQ13*(1+Calculator!$D$24/100/12) | P14: =BR13*(1+Calculator!$D$25/100/12) | Q14: =BS13*(1+Calculator!$D$26/100/12) | R14: =BT13*(1+Calculator!$D$27/100/12) | S14: =BU13*(1+Calculator!$D$28/100/12) | T14: =MAX(0,B14-Calculator!$E$11) | U14: =MAX(0,C14-Calculator!$E$12) | V14: =MAX(0,D14-Calculator!$E$13) | W14: =MAX(0,E14-Calculator!$E$14) | X14: =MAX(0,F14-Calculator!$E$15) | Y14: =MAX(0,G14-Calculator!$E$16) | Z14: =MAX(0,H14-Calculator!$E$17) | AA14: =MAX(0,I14-Calculator!$E$18) | AB14: =MAX(0,J14-Calculator!$E$19) | AC14: =MAX(0,K14-Calculator!$E$20) | AD14: =MAX(0,L14-Calculator!$E$21) | AE14: =MAX(0,M14-Calculator!$E$22) | AF14: =MAX(0,N14-Calculator!$E$23) | AG14: =MAX(0,O14-Calculator!$E$24) | AH14: =MAX(0,P14-Calculator!$E$25) | AI14: =MAX(0,Q14-Calculator!$E$26) | AJ14: =MAX(0,R14-Calculator!$E$27) | AK14: =MAX(0,S14-Calculator!$E$28) | AL14: =MAX(0,MIN(T14,BX14-SUMPRODUCT(($T$2:$AK$2<T$2)*($T14:$AK14)))) | AM14: =MAX(0,MIN(U14,BX14-SUMPRODUCT(($T$2:$AK$2<U$2)*($T14:$AK14)))) | AN14: =MAX(0,MIN(V14,BX14-SUMPRODUCT(($T$2:$AK$2<V$2)*($T14:$AK14)))) | AO14: =MAX(0,MIN(W14,BX14-SUMPRODUCT(($T$2:$AK$2<W$2)*($T14:$AK14)))) | AP14: =MAX(0,MIN(X14,BX14-SUMPRODUCT(($T$2:$AK$2<X$2)*($T14:$AK14)))) | AQ14: =MAX(0,MIN(Y14,BX14-SUMPRODUCT(($T$2:$AK$2<Y$2)*($T14:$AK14)))) | AR14: =MAX(0,MIN(Z14,BX14-SUMPRODUCT(($T$2:$AK$2<Z$2)*($T14:$AK14)))) | AS14: =MAX(0,MIN(AA14,BX14-SUMPRODUCT(($T$2:$AK$2<AA$2)*($T14:$AK14)))) | AT14: =MAX(0,MIN(AB14,BX14-SUMPRODUCT(($T$2:$AK$2<AB$2)*($T14:$AK14)))) | AU14: =MAX(0,MIN(AC14,BX14-SUMPRODUCT(($T$2:$AK$2<AC$2)*($T14:$AK14)))) | AV14: =MAX(0,MIN(AD14,BX14-SUMPRODUCT(($T$2:$AK$2<AD$2)*($T14:$AK14)))) | AW14: =MAX(0,MIN(AE14,BX14-SUMPRODUCT(($T$2:$AK$2<AE$2)*($T14:$AK14)))) | AX14: =MAX(0,MIN(AF14,BX14-SUMPRODUCT(($T$2:$AK$2<AF$2)*($T14:$AK14)))) | AY14: =MAX(0,MIN(AG14,BX14-SUMPRODUCT(($T$2:$AK$2<AG$2)*($T14:$AK14)))) | AZ14: =MAX(0,MIN(AH14,BX14-SUMPRODUCT(($T$2:$AK$2<AH$2)*($T14:$AK14)))) | BA14: =MAX(0,MIN(AI14,BX14-SUMPRODUCT(($T$2:$AK$2<AI$2)*($T14:$AK14)))) | BB14: =MAX(0,MIN(AJ14,BX14-SUMPRODUCT(($T$2:$AK$2<AJ$2)*($T14:$AK14)))) | BC14: =MAX(0,MIN(AK14,BX14-SUMPRODUCT(($T$2:$AK$2<AK$2)*($T14:$AK14)))) | BD14: =T14-AL14 | BE14: =U14-AM14 | BF14: =V14-AN14 | BG14: =W14-AO14 | BH14: =X14-AP14 | BI14: =Y14-AQ14 | BJ14: =Z14-AR14 | BK14: =AA14-AS14 | ... BU14: =AK14-BC14 | BV14: =SUM(B14:S14) | BW14: =SUM(T14:AK14) | BX14: =MAX(0,(SUM(Calculator!$E$11:$E$28)+Calculator!$C$6)-BV14+BW14) | BY14: =SUM(BD14:BU14) | BZ14: =BV14-BY13 | CA14: =IF(A14<=IF($CD$1=0,999,$CD$1),BY14,NA()) | CB14: =IF(A14<=IF($CD$1=0,999,$CD$1),A14,NA())
A15: 12 | B15: =BD14*(1+Calculator!$D$11/100/12) | C15: =BE14*(1+Calculator!$D$12/100/12) | D15: =BF14*(1+Calculator!$D$13/100/12) | E15: =BG14*(1+Calculator!$D$14/100/12) | F15: =BH14*(1+Calculator!$D$15/100/12) | G15: =BI14*(1+Calculator!$D$16/100/12) | H15: =BJ14*(1+Calculator!$D$17/100/12) | I15: =BK14*(1+Calculator!$D$18/100/12) | J15: =BL14*(1+Calculator!$D$19/100/12) | K15: =BM14*(1+Calculator!$D$20/100/12) | L15: =BN14*(1+Calculator!$D$21/100/12) | M15: =BO14*(1+Calculator!$D$22/100/12) | N15: =BP14*(1+Calculator!$D$23/100/12) | O15: =BQ14*(1+Calculator!$D$24/100/12) | P15: =BR14*(1+Calculator!$D$25/100/12) | Q15: =BS14*(1+Calculator!$D$26/100/12) | R15: =BT14*(1+Calculator!$D$27/100/12) | S15: =BU14*(1+Calculator!$D$28/100/12) | T15: =MAX(0,B15-Calculator!$E$11) | U15: =MAX(0,C15-Calculator!$E$12) | V15: =MAX(0,D15-Calculator!$E$13) | W15: =MAX(0,E15-Calculator!$E$14) | X15: =MAX(0,F15-Calculator!$E$15) | Y15: =MAX(0,G15-Calculator!$E$16) | Z15: =MAX(0,H15-Calculator!$E$17) | AA15: =MAX(0,I15-Calculator!$E$18) | AB15: =MAX(0,J15-Calculator!$E$19) | AC15: =MAX(0,K15-Calculator!$E$20) | AD15: =MAX(0,L15-Calculator!$E$21) | AE15: =MAX(0,M15-Calculator!$E$22) | AF15: =MAX(0,N15-Calculator!$E$23) | AG15: =MAX(0,O15-Calculator!$E$24) | AH15: =MAX(0,P15-Calculator!$E$25) | AI15: =MAX(0,Q15-Calculator!$E$26) | AJ15: =MAX(0,R15-Calculator!$E$27) | AK15: =MAX(0,S15-Calculator!$E$28) | AL15: =MAX(0,MIN(T15,BX15-SUMPRODUCT(($T$2:$AK$2<T$2)*($T15:$AK15)))) | AM15: =MAX(0,MIN(U15,BX15-SUMPRODUCT(($T$2:$AK$2<U$2)*($T15:$AK15)))) | AN15: =MAX(0,MIN(V15,BX15-SUMPRODUCT(($T$2:$AK$2<V$2)*($T15:$AK15)))) | AO15: =MAX(0,MIN(W15,BX15-SUMPRODUCT(($T$2:$AK$2<W$2)*($T15:$AK15)))) | AP15: =MAX(0,MIN(X15,BX15-SUMPRODUCT(($T$2:$AK$2<X$2)*($T15:$AK15)))) | AQ15: =MAX(0,MIN(Y15,BX15-SUMPRODUCT(($T$2:$AK$2<Y$2)*($T15:$AK15)))) | AR15: =MAX(0,MIN(Z15,BX15-SUMPRODUCT(($T$2:$AK$2<Z$2)*($T15:$AK15)))) | AS15: =MAX(0,MIN(AA15,BX15-SUMPRODUCT(($T$2:$AK$2<AA$2)*($T15:$AK15)))) | AT15: =MAX(0,MIN(AB15,BX15-SUMPRODUCT(($T$2:$AK$2<AB$2)*($T15:$AK15)))) | AU15: =MAX(0,MIN(AC15,BX15-SUMPRODUCT(($T$2:$AK$2<AC$2)*($T15:$AK15)))) | AV15: =MAX(0,MIN(AD15,BX15-SUMPRODUCT(($T$2:$AK$2<AD$2)*($T15:$AK15)))) | AW15: =MAX(0,MIN(AE15,BX15-SUMPRODUCT(($T$2:$AK$2<AE$2)*($T15:$AK15)))) | AX15: =MAX(0,MIN(AF15,BX15-SUMPRODUCT(($T$2:$AK$2<AF$2)*($T15:$AK15)))) | AY15: =MAX(0,MIN(AG15,BX15-SUMPRODUCT(($T$2:$AK$2<AG$2)*($T15:$AK15)))) | AZ15: =MAX(0,MIN(AH15,BX15-SUMPRODUCT(($T$2:$AK$2<AH$2)*($T15:$AK15)))) | BA15: =MAX(0,MIN(AI15,BX15-SUMPRODUCT(($T$2:$AK$2<AI$2)*($T15:$AK15)))) | BB15: =MAX(0,MIN(AJ15,BX15-SUMPRODUCT(($T$2:$AK$2<AJ$2)*($T15:$AK15)))) | BC15: =MAX(0,MIN(AK15,BX15-SUMPRODUCT(($T$2:$AK$2<AK$2)*($T15:$AK15)))) | BD15: =T15-AL15 | BE15: =U15-AM15 | BF15: =V15-AN15 | BG15: =W15-AO15 | BH15: =X15-AP15 | BI15: =Y15-AQ15 | BJ15: =Z15-AR15 | BK15: =AA15-AS15 | ... BU15: =AK15-BC15 | BV15: =SUM(B15:S15) | BW15: =SUM(T15:AK15) | BX15: =MAX(0,(SUM(Calculator!$E$11:$E$28)+Calculator!$C$6)-BV15+BW15) | BY15: =SUM(BD15:BU15) | BZ15: =BV15-BY14 | CA15: =IF(A15<=IF($CD$1=0,999,$CD$1),BY15,NA()) | CB15: =IF(A15<=IF($CD$1=0,999,$CD$1),A15,NA())
... A363: 360 | B363: =BD362*(1+Calculator!$D$11/100/12) | C363: =BE362*(1+Calculator!$D$12/100/12) | D363: =BF362*(1+Calculator!$D$13/100/12) | E363: =BG362*(1+Calculator!$D$14/100/12) | F363: =BH362*(1+Calculator!$D$15/100/12) | G363: =BI362*(1+Calculator!$D$16/100/12) | H363: =BJ362*(1+Calculator!$D$17/100/12) | I363: =BK362*(1+Calculator!$D$18/100/12) | J363: =BL362*(1+Calculator!$D$19/100/12) | K363: =BM362*(1+Calculator!$D$20/100/12) | L363: =BN362*(1+Calculator!$D$21/100/12) | M363: =BO362*(1+Calculator!$D$22/100/12) | N363: =BP362*(1+Calculator!$D$23/100/12) | O363: =BQ362*(1+Calculator!$D$24/100/12) | P363: =BR362*(1+Calculator!$D$25/100/12) | Q363: =BS362*(1+Calculator!$D$26/100/12) | R363: =BT362*(1+Calculator!$D$27/100/12) | S363: =BU362*(1+Calculator!$D$28/100/12) | T363: =MAX(0,B363-Calculator!$E$11) | U363: =MAX(0,C363-Calculator!$E$12) | V363: =MAX(0,D363-Calculator!$E$13) | W363: =MAX(0,E363-Calculator!$E$14) | X363: =MAX(0,F363-Calculator!$E$15) | Y363: =MAX(0,G363-Calculator!$E$16) | Z363: =MAX(0,H363-Calculator!$E$17) | AA363: =MAX(0,I363-Calculator!$E$18) | AB363: =MAX(0,J363-Calculator!$E$19) | AC363: =MAX(0,K363-Calculator!$E$20) | AD363: =MAX(0,L363-Calculator!$E$21) | AE363: =MAX(0,M363-Calculator!$E$22) | AF363: =MAX(0,N363-Calculator!$E$23) | AG363: =MAX(0,O363-Calculator!$E$24) | AH363: =MAX(0,P363-Calculator!$E$25) | AI363: =MAX(0,Q363-Calculator!$E$26) | AJ363: =MAX(0,R363-Calculator!$E$27) | AK363: =MAX(0,S363-Calculator!$E$28) | AL363: =MAX(0,MIN(T363,BX363-SUMPRODUCT(($T$2:$AK$2<T$2)*($T363:$AK363)))) | AM363: =MAX(0,MIN(U363,BX363-SUMPRODUCT(($T$2:$AK$2<U$2)*($T363:$AK363)))) | AN363: =MAX(0,MIN(V363,BX363-SUMPRODUCT(($T$2:$AK$2<V$2)*($T363:$AK363)))) | AO363: =MAX(0,MIN(W363,BX363-SUMPRODUCT(($T$2:$AK$2<W$2)*($T363:$AK363)))) | AP363: =MAX(0,MIN(X363,BX363-SUMPRODUCT(($T$2:$AK$2<X$2)*($T363:$AK363)))) | AQ363: =MAX(0,MIN(Y363,BX363-SUMPRODUCT(($T$2:$AK$2<Y$2)*($T363:$AK363)))) | AR363: =MAX(0,MIN(Z363,BX363-SUMPRODUCT(($T$2:$AK$2<Z$2)*($T363:$AK363)))) | AS363: =MAX(0,MIN(AA363,BX363-SUMPRODUCT(($T$2:$AK$2<AA$2)*($T363:$AK363)))) | AT363: =MAX(0,MIN(AB363,BX363-SUMPRODUCT(($T$2:$AK$2<AB$2)*($T363:$AK363)))) | AU363: =MAX(0,MIN(AC363,BX363-SUMPRODUCT(($T$2:$AK$2<AC$2)*($T363:$AK363)))) | AV363: =MAX(0,MIN(AD363,BX363-SUMPRODUCT(($T$2:$AK$2<AD$2)*($T363:$AK363)))) | AW363: =MAX(0,MIN(AE363,BX363-SUMPRODUCT(($T$2:$AK$2<AE$2)*($T363:$AK363)))) | AX363: =MAX(0,MIN(AF363,BX363-SUMPRODUCT(($T$2:$AK$2<AF$2)*($T363:$AK363)))) | AY363: =MAX(0,MIN(AG363,BX363-SUMPRODUCT(($T$2:$AK$2<AG$2)*($T363:$AK363)))) | AZ363: =MAX(0,MIN(AH363,BX363-SUMPRODUCT(($T$2:$AK$2<AH$2)*($T363:$AK363)))) | BA363: =MAX(0,MIN(AI363,BX363-SUMPRODUCT(($T$2:$AK$2<AI$2)*($T363:$AK363)))) | BB363: =MAX(0,MIN(AJ363,BX363-SUMPRODUCT(($T$2:$AK$2<AJ$2)*($T363:$AK363)))) | BC363: =MAX(0,MIN(AK363,BX363-SUMPRODUCT(($T$2:$AK$2<AK$2)*($T363:$AK363)))) | BD363: =T363-AL363 | BE363: =U363-AM363 | BF363: =V363-AN363 | BG363: =W363-AO363 | BH363: =X363-AP363 | BI363: =Y363-AQ363 | BJ363: =Z363-AR363 | BK363: =AA363-AS363 | ... BU363: =AK363-BC363 | BV363: =SUM(B363:S363) | BW363: =SUM(T363:AK363) | BX363: =MAX(0,(SUM(Calculator!$E$11:$E$28)+Calculator!$C$6)-BV363+BW363) | BY363: =SUM(BD363:BU363) | BZ363: =BV363-BY362 | CA363: =IF(A363<=IF($CD$1=0,999,$CD$1),BY363,NA()) | CB363: =IF(A363<=IF($CD$1=0,999,$CD$1),A363,NA())
